multi_maths/__init__.py
multi_maths/__main__.py
multi_maths/__version__.py
multi_maths/cli.py
multi_maths/core.py
multi_maths/filters.py
multi_maths/info.py
multi_maths/multi_maths.py
multi_maths/languages/en.ini
multi_maths/languages/es.ini
multi_maths/mm_arithmetic/__init__.py
multi_maths/mm_arithmetic/mm_arithmetic.py
multi_maths/mm_geometry/__init__.py
multi_maths/mm_geometry/mm_geometry.py
multi_maths/mm_statistics/__init__.py
multi_maths/mm_statistics/mm_statistics.py
multi_maths/tests/__init__.py
multi_maths/tests/test_arithmetic.py
multi_maths/tests/test_core.py
multi_maths/tests/test_filters.py
multi_maths/tests/test_geometry.py
multi_maths/tests/test_info.py
multi_maths/tests/test_statistics.py
multi_maths-1.0.7.dist-info/LICENSE
multi_maths-1.0.7.dist-info/METADATA
multi_maths-1.0.7.dist-info/WHEEL
multi_maths-1.0.7.dist-info/entry_points.txt
multi_maths-1.0.7.dist-info/top_level.txt
multi_maths-1.0.7.dist-info/RECORD
