Metadata-Version: 2.1
Name: multi-maths
Version: 1.0.7
Summary: An arithmetic, geometry & statistics package.
Home-page: https://github.com/gsmx64/python-adv-bootcamp-cf/tree/main/class03/challenge
Author: Gonzalo Mahserdjian
Author-email: Gonzalo Mahserdjian <gsmx64@outlook.com>
License: GNU/GPL version 3
Project-URL: Homepage, https://github.com/gsmx64/python-adv-bootcamp-cf/tree/main/class03/challenge
Project-URL: Bug Tracker, https://github.com/gsmx64/python-adv-bootcamp-cf/issues
Keywords: multi maths,arithmetic,geometry,statistics
Classifier: Programming Language :: Python :: 3
Classifier: License :: OSI Approved :: GNU General Public License v3 (GPLv3)
Classifier: Operating System :: OS Independent
Requires-Python: >=3.7
License-File: LICENSE
